particleman/__init__.py
particleman/core.py
particleman/dop.py
particleman/filter.py
particleman/libst.cpython-36m-darwin.so
particleman/plotting.py
particleman/st.py
particleman-0.3.0.dist-info/COPYING.txt
particleman-0.3.0.dist-info/LICENSE.txt
particleman-0.3.0.dist-info/METADATA
particleman-0.3.0.dist-info/WHEEL
particleman-0.3.0.dist-info/top_level.txt
particleman-0.3.0.dist-info/RECORD
