Metadata-Version: 2.1
Name: particleman
Version: 0.3.0
Summary: Particle motion analysis for seismic surface waves
Home-page: http://github.com/lanl-seismoacoustics/particleman
Author: Jonathan MacCarthy
Author-email: jkmacc@lanl.gov
License: UNKNOWN
Platform: UNKNOWN
Requires-Dist: numpy
